[
  { "path": "application-wrapper/Looksyk/package.json", "type": "json" },
  { "path": "application-wrapper/Looksyk/package-lock.json", "type": "json" },
  { "path": "frontend/looksyk/package.json", "type": "json" },
  { "path": "frontend/looksyk/package-lock.json", "type": "json" },
  { "path": "backend/Cargo.toml", "type": "cargo" },
  { "path": "backend/Cargo.lock", "type": "cargo-lock", "package": "looksyk" },
  { "path": "PKGBUILD", "type": "pkgbuild" },
  { "path": "de.sebastianruziczka.looksyk.yml", "type": "yaml-source-url" },
  { "path": "de.sebastianruziczka.looksyk.metainfo.xml", "type": "metainfo-xml" }
]

